libname/VoiceType.py
libname/__init__.py
VoiceType-0.0.2.dist-info/METADATA
VoiceType-0.0.2.dist-info/WHEEL
VoiceType-0.0.2.dist-info/top_level.txt
VoiceType-0.0.2.dist-info/RECORD
